README.rst
setup.py
edu_py_logger/__init__.py
edu_py_logger/config.py
edu_py_logger/logger.py
edu_py_logger/middlewares.py
edu_py_logger/utils.py
edu_py_logger.egg-info/PKG-INFO
edu_py_logger.egg-info/SOURCES.txt
edu_py_logger.egg-info/dependency_links.txt
edu_py_logger.egg-info/requires.txt
edu_py_logger.egg-info/top_level.txt
tests/__init__.py
tests/test_config.py
tests/test_logger.py
tests/test_utils.py