Metadata-Version: 2.1
Name: edu-py-logger
Version: 1.6
Summary: UNKNOWN
Home-page: https://github.com/BlipIQSciences/edu-py-logger
Author: Julia F
Author-email: julia@blipiq.com
License: MIT
Keywords: fastapi logging
Platform: UNKNOWN
Classifier: Development Status :: 3 - Alpha
Classifier: License :: OSI Approved :: MIT License
Classifier: Programming Language :: Python :: 3.8
Classifier: Topic :: System :: Logging
